[{"name":"Tachiyomi: Leviatan Scans","pkg":"eu.kanade.tachiyomi.extension.all.leviatanscans","apk":"tachiyomi-all.leviatanscans-v1.2.2.apk","lang":"all","code":2,"version":"1.2.2","nsfw":0},{"name":"Tachiyomi: AkuManga","pkg":"eu.kanade.tachiyomi.extension.ar.akumanga","apk":"tachiyomi-ar.akumanga-v1.2.1.apk","lang":"ar","code":1,"version":"1.2.1","nsfw":0},{"name":"Tachiyomi: Asgard Team","pkg":"eu.kanade.tachiyomi.extension.ar.asgardteam","apk":"tachiyomi-ar.asgardteam-v1.2.1.apk","lang":"ar","code":1,"version":"1.2.1","nsfw":0},{"name":"Tachiyomi: Azora","pkg":"eu.kanade.tachiyomi.extension.ar.azora","apk":"tachiyomi-ar.azora-v1.2.1.apk","lang":"ar","code":1,"version":"1.2.1","nsfw":0},{"name":"Tachiyomi: شبكة كونان العربية","pkg":"eu.kanade.tachiyomi.extension.ar.detectiveconanar","apk":"tachiyomi-ar.detectiveconanar-v1.2.1.apk","lang":"ar","code":1,"version":"1.2.1","nsfw":0},{"name":"Tachiyomi: موقع لترجمة المانجا","pkg":"eu.kanade.tachiyomi.extension.ar.goldenmanga","apk":"tachiyomi-ar.goldenmanga-v1.2.1.apk","lang":"ar","code":1,"version":"1.2.1","nsfw":0},{"name":"Tachiyomi: KingzManga","pkg":"eu.kanade.tachiyomi.extension.ar.kingzmanga","apk":"tachiyomi-ar.kingzmanga-v1.2.1.apk","lang":"ar","code":1,"version":"1.2.1","nsfw":0},{"name":"Tachiyomi: Agent of Change Translations","pkg":"eu.kanade.tachiyomi.extension.en.agentofchangetranslations","apk":"tachiyomi-en.agentofchangetranslations-v1.2.1.apk","lang":"en","code":1,"version":"1.2.1","nsfw":0},{"name":"Tachiyomi: AllPornComic","pkg":"eu.kanade.tachiyomi.extension.en.allporncomic","apk":"tachiyomi-en.allporncomic-v1.2.1.apk","lang":"en","code":1,"version":"1.2.1","nsfw":0},{"name":"Tachiyomi: Aloalivn","pkg":"eu.kanade.tachiyomi.extension.en.aloalivn","apk":"tachiyomi-en.aloalivn-v1.2.1.apk","lang":"en","code":1,"version":"1.2.1","nsfw":0},{"name":"Tachiyomi: AniMangaEs","pkg":"eu.kanade.tachiyomi.extension.en.animangaes","apk":"tachiyomi-en.animangaes-v1.2.1.apk","lang":"en","code":1,"version":"1.2.1","nsfw":0},{"name":"Tachiyomi: Arang Scans","pkg":"eu.kanade.tachiyomi.extension.en.arangscans","apk":"tachiyomi-en.arangscans-v1.2.1.apk","lang":"en","code":1,"version":"1.2.1","nsfw":0},{"name":"Tachiyomi: Astral Library","pkg":"eu.kanade.tachiyomi.extension.en.astrallibrary","apk":"tachiyomi-en.astrallibrary-v1.2.1.apk","lang":"en","code":1,"version":"1.2.1","nsfw":0},{"name":"Tachiyomi: BestManhua","pkg":"eu.kanade.tachiyomi.extension.en.bestmanhua","apk":"tachiyomi-en.bestmanhua-v1.2.2.apk","lang":"en","code":2,"version":"1.2.2","nsfw":0},{"name":"Tachiyomi: BoysLove","pkg":"eu.kanade.tachiyomi.extension.en.boyslove","apk":"tachiyomi-en.boyslove-v1.2.1.apk","lang":"en","code":1,"version":"1.2.1","nsfw":0},{"name":"Tachiyomi: CatOnHeadTranslations","pkg":"eu.kanade.tachiyomi.extension.en.catonheadtranslations","apk":"tachiyomi-en.catonheadtranslations-v1.2.1.apk","lang":"en","code":1,"version":"1.2.1","nsfw":0},{"name":"Tachiyomi: Chibi Manga","pkg":"eu.kanade.tachiyomi.extension.en.chibimanga","apk":"tachiyomi-en.chibimanga-v1.2.1.apk","lang":"en","code":1,"version":"1.2.1","nsfw":0},{"name":"Tachiyomi: ComicKiba","pkg":"eu.kanade.tachiyomi.extension.en.comickiba","apk":"tachiyomi-en.comickiba-v1.2.1.apk","lang":"en","code":1,"version":"1.2.1","nsfw":0},{"name":"Tachiyomi: Decadence Scans","pkg":"eu.kanade.tachiyomi.extension.en.decadencescans","apk":"tachiyomi-en.decadencescans-v1.2.1.apk","lang":"en","code":1,"version":"1.2.1","nsfw":0},{"name":"Tachiyomi: Disaster Scans","pkg":"eu.kanade.tachiyomi.extension.en.disasterscans","apk":"tachiyomi-en.disasterscans-v1.2.1.apk","lang":"en","code":1,"version":"1.2.1","nsfw":0},{"name":"Tachiyomi: Dream Manga","pkg":"eu.kanade.tachiyomi.extension.en.dreammanga","apk":"tachiyomi-en.dreammanga-v1.2.1.apk","lang":"en","code":1,"version":"1.2.1","nsfw":0},{"name":"Tachiyomi: Edelgarde Scans","pkg":"eu.kanade.tachiyomi.extension.en.edelgardescans","apk":"tachiyomi-en.edelgardescans-v1.2.1.apk","lang":"en","code":1,"version":"1.2.1","nsfw":0},{"name":"Tachiyomi: 8Muses","pkg":"eu.kanade.tachiyomi.extension.en.eightmuses","apk":"tachiyomi-en.eightmuses-v1.2.1.apk","lang":"en","code":1,"version":"1.2.1","nsfw":1},{"name":"Tachiyomi: Einherjar Scan","pkg":"eu.kanade.tachiyomi.extension.en.einherjarscan","apk":"tachiyomi-en.einherjarscan-v1.2.1.apk","lang":"en","code":1,"version":"1.2.1","nsfw":0},{"name":"Tachiyomi: Erofus","pkg":"eu.kanade.tachiyomi.extension.en.erofus","apk":"tachiyomi-en.erofus-v1.2.1.apk","lang":"en","code":1,"version":"1.2.1","nsfw":1},{"name":"Tachiyomi: 1st Kiss","pkg":"eu.kanade.tachiyomi.extension.en.firstkissmanga","apk":"tachiyomi-en.firstkissmanga-v1.2.2.apk","lang":"en","code":2,"version":"1.2.2","nsfw":0},{"name":"Tachiyomi: 1st Kiss Manhua","pkg":"eu.kanade.tachiyomi.extension.en.firstkissmanhua","apk":"tachiyomi-en.firstkissmanhua-v1.2.1.apk","lang":"en","code":1,"version":"1.2.1","nsfw":0},{"name":"Tachiyomi: FreeWebtoonCoins","pkg":"eu.kanade.tachiyomi.extension.en.freewebtooncoins","apk":"tachiyomi-en.freewebtooncoins-v1.2.1.apk","lang":"en","code":1,"version":"1.2.1","nsfw":0},{"name":"Tachiyomi: Gourmet Scans","pkg":"eu.kanade.tachiyomi.extension.en.gourmetscans","apk":"tachiyomi-en.gourmetscans-v1.2.1.apk","lang":"en","code":1,"version":"1.2.1","nsfw":0},{"name":"Tachiyomi: Graze Scans","pkg":"eu.kanade.tachiyomi.extension.en.grazescans","apk":"tachiyomi-en.grazescans-v1.2.1.apk","lang":"en","code":1,"version":"1.2.1","nsfw":0},{"name":"Tachiyomi: Hatigarm Scans","pkg":"eu.kanade.tachiyomi.extension.en.hatigarmscans","apk":"tachiyomi-en.hatigarmscans-v1.2.2.apk","lang":"en","code":2,"version":"1.2.2","nsfw":0},{"name":"Tachiyomi: Hero Manhua","pkg":"eu.kanade.tachiyomi.extension.en.heromanhua","apk":"tachiyomi-en.heromanhua-v1.2.1.apk","lang":"en","code":1,"version":"1.2.1","nsfw":0},{"name":"Tachiyomi: Heroz Scanlation","pkg":"eu.kanade.tachiyomi.extension.en.herozscanlation","apk":"tachiyomi-en.herozscanlation-v1.2.1.apk","lang":"en","code":1,"version":"1.2.1","nsfw":0},{"name":"Tachiyomi: Hiperdex","pkg":"eu.kanade.tachiyomi.extension.en.hiperdex","apk":"tachiyomi-en.hiperdex-v1.2.1.apk","lang":"en","code":1,"version":"1.2.1","nsfw":0},{"name":"Tachiyomi: Hscans","pkg":"eu.kanade.tachiyomi.extension.en.hscans","apk":"tachiyomi-en.hscans-v1.2.1.apk","lang":"en","code":1,"version":"1.2.1","nsfw":0},{"name":"Tachiyomi: Hunlight Scans","pkg":"eu.kanade.tachiyomi.extension.en.hunlightscans","apk":"tachiyomi-en.hunlightscans-v1.2.1.apk","lang":"en","code":1,"version":"1.2.1","nsfw":0},{"name":"Tachiyomi: Immortal Updates","pkg":"eu.kanade.tachiyomi.extension.en.immortalupdates","apk":"tachiyomi-en.immortalupdates-v1.2.1.apk","lang":"en","code":1,"version":"1.2.1","nsfw":0},{"name":"Tachiyomi: IsekaiScan.com","pkg":"eu.kanade.tachiyomi.extension.en.isekaiscancom","apk":"tachiyomi-en.isekaiscancom-v1.2.1.apk","lang":"en","code":1,"version":"1.2.1","nsfw":0},{"name":"Tachiyomi: Its Your Right Manhua","pkg":"eu.kanade.tachiyomi.extension.en.itsyourrightmanhua","apk":"tachiyomi-en.itsyourrightmanhua-v1.2.1.apk","lang":"en","code":1,"version":"1.2.1","nsfw":0},{"name":"Tachiyomi: JJutsuScans","pkg":"eu.kanade.tachiyomi.extension.en.jjutsuscans","apk":"tachiyomi-en.jjutsuscans-v1.2.1.apk","lang":"en","code":1,"version":"1.2.1","nsfw":0},{"name":"Tachiyomi: KisekiManga","pkg":"eu.kanade.tachiyomi.extension.en.kisekimanga","apk":"tachiyomi-en.kisekimanga-v1.2.1.apk","lang":"en","code":1,"version":"1.2.1","nsfw":0},{"name":"Tachiyomi: Kissmanga.in","pkg":"eu.kanade.tachiyomi.extension.en.kissmangain","apk":"tachiyomi-en.kissmangain-v1.2.1.apk","lang":"en","code":1,"version":"1.2.1","nsfw":0},{"name":"Tachiyomi: LetItGo Scans","pkg":"eu.kanade.tachiyomi.extension.en.letitgoscans","apk":"tachiyomi-en.letitgoscans-v1.2.1.apk","lang":"en","code":1,"version":"1.2.1","nsfw":0},{"name":"Tachiyomi: Mangabat","pkg":"eu.kanade.tachiyomi.extension.en.mangabat","apk":"tachiyomi-en.mangabat-v1.2.1.apk","lang":"en","code":1,"version":"1.2.1","nsfw":0},{"name":"Tachiyomi: Mangairo","pkg":"eu.kanade.tachiyomi.extension.en.mangairo","apk":"tachiyomi-en.mangairo-v1.2.1.apk","lang":"en","code":1,"version":"1.2.1","nsfw":0},{"name":"Tachiyomi: Mangakakalot","pkg":"eu.kanade.tachiyomi.extension.en.mangakakalot","apk":"tachiyomi-en.mangakakalot-v1.2.1.apk","lang":"en","code":1,"version":"1.2.1","nsfw":0},{"name":"Tachiyomi: Mangakakalots (unoriginal)","pkg":"eu.kanade.tachiyomi.extension.en.mangakakalots","apk":"tachiyomi-en.mangakakalots-v1.2.1.apk","lang":"en","code":1,"version":"1.2.1","nsfw":0},{"name":"Tachiyomi: Manganelo","pkg":"eu.kanade.tachiyomi.extension.en.manganelo","apk":"tachiyomi-en.manganelo-v1.2.1.apk","lang":"en","code":1,"version":"1.2.1","nsfw":0},{"name":"Tachiyomi: Mangazuki.online","pkg":"eu.kanade.tachiyomi.extension.en.mangazukionline","apk":"tachiyomi-en.mangazukionline-v1.2.1.apk","lang":"en","code":1,"version":"1.2.1","nsfw":0},{"name":"Tachiyomi: Method Scans","pkg":"eu.kanade.tachiyomi.extension.en.methodscans","apk":"tachiyomi-en.methodscans-v1.2.1.apk","lang":"en","code":1,"version":"1.2.1","nsfw":0},{"name":"Tachiyomi: Reaper Scans","pkg":"eu.kanade.tachiyomi.extension.en.reaperscans","apk":"tachiyomi-en.reaperscans-v1.2.1.apk","lang":"en","code":1,"version":"1.2.1","nsfw":0},{"name":"Tachiyomi: SecretScans","pkg":"eu.kanade.tachiyomi.extension.en.secretscans","apk":"tachiyomi-en.secretscans-v1.2.1.apk","lang":"en","code":1,"version":"1.2.1","nsfw":0},{"name":"Tachiyomi: Sleeping Knight Scans","pkg":"eu.kanade.tachiyomi.extension.en.sleepingknightscans","apk":"tachiyomi-en.sleepingknightscans-v1.2.1.apk","lang":"en","code":1,"version":"1.2.1","nsfw":0},{"name":"Tachiyomi: The Nonames Scans","pkg":"eu.kanade.tachiyomi.extension.en.thenonamesscans","apk":"tachiyomi-en.thenonamesscans-v1.2.1.apk","lang":"en","code":1,"version":"1.2.1","nsfw":0},{"name":"Tachiyomi: WhimSubs","pkg":"eu.kanade.tachiyomi.extension.en.whimsubs","apk":"tachiyomi-en.whimsubs-v1.2.1.apk","lang":"en","code":1,"version":"1.2.1","nsfw":0},{"name":"Tachiyomi: ZeroScans","pkg":"eu.kanade.tachiyomi.extension.en.zeroscans","apk":"tachiyomi-en.zeroscans-v1.2.1.apk","lang":"en","code":1,"version":"1.2.1","nsfw":0},{"name":"Tachiyomi: AlianzaMarcial","pkg":"eu.kanade.tachiyomi.extension.es.alianzamarcial","apk":"tachiyomi-es.alianzamarcial-v1.2.1.apk","lang":"es","code":1,"version":"1.2.1","nsfw":0},{"name":"Tachiyomi: ApollComics","pkg":"eu.kanade.tachiyomi.extension.es.apollcomics","apk":"tachiyomi-es.apollcomics-v1.2.1.apk","lang":"es","code":1,"version":"1.2.1","nsfw":0},{"name":"Tachiyomi: CopyPasteScan","pkg":"eu.kanade.tachiyomi.extension.es.copypastescan","apk":"tachiyomi-es.copypastescan-v1.2.1.apk","lang":"es","code":1,"version":"1.2.1","nsfw":0},{"name":"Tachiyomi: DoujinHentai","pkg":"eu.kanade.tachiyomi.extension.es.doujinhentai","apk":"tachiyomi-es.doujinhentai-v1.2.1.apk","lang":"es","code":1,"version":"1.2.1","nsfw":1},{"name":"Tachiyomi: Hunter Fansub","pkg":"eu.kanade.tachiyomi.extension.es.hunterfansub","apk":"tachiyomi-es.hunterfansub-v1.2.1.apk","lang":"es","code":1,"version":"1.2.1","nsfw":0},{"name":"Tachiyomi: ATM-Subs","pkg":"eu.kanade.tachiyomi.extension.fr.atmsubs","apk":"tachiyomi-fr.atmsubs-v1.2.1.apk","lang":"fr","code":1,"version":"1.2.1","nsfw":0},{"name":"Tachiyomi: Comics Valley","pkg":"eu.kanade.tachiyomi.extension.hi.comicsvalley","apk":"tachiyomi-hi.comicsvalley-v1.2.1.apk","lang":"hi","code":1,"version":"1.2.1","nsfw":1},{"name":"Tachiyomi: DoujinYosh","pkg":"eu.kanade.tachiyomi.extension.id.doujinyosh","apk":"tachiyomi-id.doujinyosh-v1.2.1.apk","lang":"id","code":1,"version":"1.2.1","nsfw":0},{"name":"Tachiyomi: KlikManga","pkg":"eu.kanade.tachiyomi.extension.id.klikmanga","apk":"tachiyomi-id.klikmanga-v1.2.1.apk","lang":"id","code":1,"version":"1.2.1","nsfw":0},{"name":"Tachiyomi: Kombatch","pkg":"eu.kanade.tachiyomi.extension.id.kombatch","apk":"tachiyomi-id.kombatch-v1.2.1.apk","lang":"id","code":1,"version":"1.2.1","nsfw":0},{"name":"Tachiyomi: Argos Scan","pkg":"eu.kanade.tachiyomi.extension.pt.argosscan","apk":"tachiyomi-pt.argosscan-v1.2.1.apk","lang":"pt","code":1,"version":"1.2.1","nsfw":0},{"name":"Tachiyomi: Darkyu Realm","pkg":"eu.kanade.tachiyomi.extension.pt.darkyurealm","apk":"tachiyomi-pt.darkyurealm-v1.2.1.apk","lang":"pt","code":1,"version":"1.2.1","nsfw":0},{"name":"Tachiyomi: Drope Scan","pkg":"eu.kanade.tachiyomi.extension.pt.dropescan","apk":"tachiyomi-pt.dropescan-v1.2.1.apk","lang":"pt","code":1,"version":"1.2.1","nsfw":0},{"name":"Tachiyomi: FDM Scan","pkg":"eu.kanade.tachiyomi.extension.pt.fdmscan","apk":"tachiyomi-pt.fdmscan-v1.2.1.apk","lang":"pt","code":1,"version":"1.2.1","nsfw":0},{"name":"Tachiyomi: Furio Scans","pkg":"eu.kanade.tachiyomi.extension.pt.furioscans","apk":"tachiyomi-pt.furioscans-v1.2.1.apk","lang":"pt","code":1,"version":"1.2.1","nsfw":0},{"name":"Tachiyomi: Hikari Scan","pkg":"eu.kanade.tachiyomi.extension.pt.hikariscan","apk":"tachiyomi-pt.hikariscan-v1.2.1.apk","lang":"pt","code":1,"version":"1.2.1","nsfw":0},{"name":"Tachiyomi: Ichirin No Hana Yuri","pkg":"eu.kanade.tachiyomi.extension.pt.ichirinnohanayuri","apk":"tachiyomi-pt.ichirinnohanayuri-v1.2.1.apk","lang":"pt","code":1,"version":"1.2.1","nsfw":0},{"name":"Tachiyomi: BestManga","pkg":"eu.kanade.tachiyomi.extension.ru.bestmanga","apk":"tachiyomi-ru.bestmanga-v1.2.1.apk","lang":"ru","code":1,"version":"1.2.1","nsfw":0},{"name":"Tachiyomi: Just For Fun","pkg":"eu.kanade.tachiyomi.extension.ru.justforfun","apk":"tachiyomi-ru.justforfun-v1.2.1.apk","lang":"ru","code":1,"version":"1.2.1","nsfw":0},{"name":"Tachiyomi: Bakaman","pkg":"eu.kanade.tachiyomi.extension.th.bakaman","apk":"tachiyomi-th.bakaman-v1.2.1.apk","lang":"th","code":1,"version":"1.2.1","nsfw":0},{"name":"Tachiyomi: CAT-translator","pkg":"eu.kanade.tachiyomi.extension.th.cattranslator","apk":"tachiyomi-th.cattranslator-v1.2.1.apk","lang":"th","code":1,"version":"1.2.1","nsfw":0},{"name":"Tachiyomi: Adonis Fansub","pkg":"eu.kanade.tachiyomi.extension.tr.adonisfansub","apk":"tachiyomi-tr.adonisfansub-v1.2.1.apk","lang":"tr","code":1,"version":"1.2.1","nsfw":0},{"name":"Tachiyomi: ArazNovel","pkg":"eu.kanade.tachiyomi.extension.tr.araznovel","apk":"tachiyomi-tr.araznovel-v1.2.1.apk","lang":"tr","code":1,"version":"1.2.1","nsfw":0},{"name":"Tachiyomi: Atikrost","pkg":"eu.kanade.tachiyomi.extension.tr.atikrost","apk":"tachiyomi-tr.atikrost-v1.2.1.apk","lang":"tr","code":1,"version":"1.2.1","nsfw":0},{"name":"Tachiyomi: Clover Manga","pkg":"eu.kanade.tachiyomi.extension.tr.clovermanga","apk":"tachiyomi-tr.clovermanga-v1.2.1.apk","lang":"tr","code":1,"version":"1.2.1","nsfw":0},{"name":"Tachiyomi: Cutie Pie","pkg":"eu.kanade.tachiyomi.extension.tr.cutiepie","apk":"tachiyomi-tr.cutiepie-v1.2.1.apk","lang":"tr","code":1,"version":"1.2.1","nsfw":0},{"name":"Tachiyomi: DiamondFansub","pkg":"eu.kanade.tachiyomi.extension.tr.diamondfansub","apk":"tachiyomi-tr.diamondfansub-v1.2.1.apk","lang":"tr","code":1,"version":"1.2.1","nsfw":0},{"name":"Tachiyomi: Gecenin Lordu","pkg":"eu.kanade.tachiyomi.extension.tr.geceninlordu","apk":"tachiyomi-tr.geceninlordu-v1.2.1.apk","lang":"tr","code":1,"version":"1.2.1","nsfw":0},{"name":"Tachiyomi: GuncelManga","pkg":"eu.kanade.tachiyomi.extension.tr.guncelmanga","apk":"tachiyomi-tr.guncelmanga-v1.2.1.apk","lang":"tr","code":1,"version":"1.2.1","nsfw":0},{"name":"Tachiyomi: Himera Fansub","pkg":"eu.kanade.tachiyomi.extension.tr.himerafansub","apk":"tachiyomi-tr.himerafansub-v1.2.1.apk","lang":"tr","code":1,"version":"1.2.1","nsfw":0},{"name":"Tachiyomi: BainianManga","pkg":"eu.kanade.tachiyomi.extension.zh.bainianmanga","apk":"tachiyomi-zh.bainianmanga-v1.2.2.apk","lang":"zh","code":2,"version":"1.2.2","nsfw":0},{"name":"Tachiyomi: BH3","pkg":"eu.kanade.tachiyomi.extension.zh.bh3","apk":"tachiyomi-zh.bh3-v1.2.2.apk","lang":"zh","code":2,"version":"1.2.2","nsfw":0},{"name":"Tachiyomi: Comico","pkg":"eu.kanade.tachiyomi.extension.zh.comico","apk":"tachiyomi-zh.comico-v1.2.1.apk","lang":"zh","code":1,"version":"1.2.1","nsfw":0},{"name":"Tachiyomi: CopyManga","pkg":"eu.kanade.tachiyomi.extension.zh.copymanga","apk":"tachiyomi-zh.copymanga-v1.2.5.apk","lang":"zh","code":5,"version":"1.2.5","nsfw":0},{"name":"Tachiyomi: Dmzj","pkg":"eu.kanade.tachiyomi.extension.zh.dmzj","apk":"tachiyomi-zh.dmzj-v1.2.16.apk","lang":"zh","code":16,"version":"1.2.16","nsfw":0},{"name":"Tachiyomi: Gufeng Manhua","pkg":"eu.kanade.tachiyomi.extension.zh.gufengmh","apk":"tachiyomi-zh.gufengmh-v1.2.3.apk","lang":"zh","code":3,"version":"1.2.3","nsfw":0},{"name":"Tachiyomi: Hanhankuman","pkg":"eu.kanade.tachiyomi.extension.zh.hanhankuman","apk":"tachiyomi-zh.hanhankuman-v1.2.3.apk","lang":"zh","code":3,"version":"1.2.3","nsfw":0},{"name":"Tachiyomi: Jinmantiantang","pkg":"eu.kanade.tachiyomi.extension.zh.jinmantiantang","apk":"tachiyomi-zh.jinmantiantang-v1.2.11.apk","lang":"zh","code":11,"version":"1.2.11","nsfw":1},{"name":"Tachiyomi: Kuaikanmanhua","pkg":"eu.kanade.tachiyomi.extension.zh.kuaikanmanhua","apk":"tachiyomi-zh.kuaikanmanhua-v1.2.2.apk","lang":"zh","code":2,"version":"1.2.2","nsfw":0},{"name":"Tachiyomi: Mangabz","pkg":"eu.kanade.tachiyomi.extension.zh.mangabz","apk":"tachiyomi-zh.mangabz-v1.2.1.apk","lang":"zh","code":1,"version":"1.2.1","nsfw":0},{"name":"Tachiyomi: ManhuaDB","pkg":"eu.kanade.tachiyomi.extension.zh.manhuadb","apk":"tachiyomi-zh.manhuadb-v1.2.2.apk","lang":"zh","code":2,"version":"1.2.2","nsfw":0},{"name":"Tachiyomi: Manhuadui","pkg":"eu.kanade.tachiyomi.extension.zh.manhuadui","apk":"tachiyomi-zh.manhuadui-v1.2.14.apk","lang":"zh","code":14,"version":"1.2.14","nsfw":0},{"name":"Tachiyomi: ManHuaGui","pkg":"eu.kanade.tachiyomi.extension.zh.manhuagui","apk":"tachiyomi-zh.manhuagui-v1.2.7.apk","lang":"zh","code":7,"version":"1.2.7","nsfw":0},{"name":"Tachiyomi: Manhuaren","pkg":"eu.kanade.tachiyomi.extension.zh.manhuaren","apk":"tachiyomi-zh.manhuaren-v1.2.7.apk","lang":"zh","code":7,"version":"1.2.7","nsfw":0},{"name":"Tachiyomi: CoCoManhua (OhManhua)","pkg":"eu.kanade.tachiyomi.extension.zh.onemanhua","apk":"tachiyomi-zh.onemanhua-v1.2.7.apk","lang":"zh","code":7,"version":"1.2.7","nsfw":0},{"name":"Tachiyomi: Pufei","pkg":"eu.kanade.tachiyomi.extension.zh.pufei","apk":"tachiyomi-zh.pufei-v1.2.5.apk","lang":"zh","code":5,"version":"1.2.5","nsfw":0},{"name":"Tachiyomi: Qimiaomh","pkg":"eu.kanade.tachiyomi.extension.zh.qimiaomh","apk":"tachiyomi-zh.qimiaomh-v1.2.1.apk","lang":"zh","code":1,"version":"1.2.1","nsfw":0},{"name":"Tachiyomi: QiXiManhua","pkg":"eu.kanade.tachiyomi.extension.zh.qiximh","apk":"tachiyomi-zh.qiximh-v1.2.2.apk","lang":"zh","code":2,"version":"1.2.2","nsfw":0},{"name":"Tachiyomi: Tohomh123","pkg":"eu.kanade.tachiyomi.extension.zh.tohomh123","apk":"tachiyomi-zh.tohomh123-v1.2.2.apk","lang":"zh","code":2,"version":"1.2.2","nsfw":0},{"name":"Tachiyomi: WNACG","pkg":"eu.kanade.tachiyomi.extension.zh.wnacg","apk":"tachiyomi-zh.wnacg-v1.2.4.apk","lang":"zh","code":4,"version":"1.2.4","nsfw":0},{"name":"Tachiyomi: WuqiManga","pkg":"eu.kanade.tachiyomi.extension.zh.wuqimanga","apk":"tachiyomi-zh.wuqimanga-v1.2.1.apk","lang":"zh","code":1,"version":"1.2.1","nsfw":0}]
